gpdconfig/__init__.py
gpdconfig/__main__.py
gpdconfig/app.py
gpdconfig/wincontrols/__init__.py
gpdconfig/wincontrols/config.py
gpdconfig/wincontrols/hardware.py
gpdconfig-1.0.3.dist-info/COPYING
gpdconfig-1.0.3.dist-info/METADATA
gpdconfig-1.0.3.dist-info/WHEEL
gpdconfig-1.0.3.dist-info/entry_points.txt
gpdconfig-1.0.3.dist-info/top_level.txt
gpdconfig-1.0.3.dist-info/RECORD
