Metadata-Version: 2.1
Name: gpdconfig
Version: 1.0.3
Summary: Configuration tool for GPD Win devices
Author-email: James Churchill <pelrun@gmail.com>
License: GNU GENERAL PUBLIC LICENSE
Project-URL: Homepage, https://github.com/pelrun/pyWinControls
Project-URL: Repository, https://github.com/pelrun/pyWinControls.git
Project-URL: Bug Tracker, https://github.com/pelrun/pyWinControls/issues
Keywords: gpd,wincontrols
Classifier: License :: OSI Approved :: GNU General Public License v3 or later (GPLv3+)
Classifier: Development Status :: 4 - Beta
Classifier: Programming Language :: Python
License-File: COPYING
Requires-Dist: hid >=1.0.5
